.gitignore
CHANGELOG.md
LICENSE
MANIFEST.in
README.md
setup.py
django_markdown2/__init__.py
django_markdown2.egg-info/PKG-INFO
django_markdown2.egg-info/SOURCES.txt
django_markdown2.egg-info/dependency_links.txt
django_markdown2.egg-info/requires.txt
django_markdown2.egg-info/top_level.txt
django_markdown2/templatetags/__init__.py
django_markdown2/templatetags/md2.py