Metadata-Version: 1.1
Name: django-markdown2
Version: 0.3.0
Summary: This is a simple app, which supplies a single template tag for markdown markup.
Home-page: http://github.com/svetlyak40wt/django-markdown2/
Author: Alexander Artemenko
Author-email: svetlyak.40wt@gmail.com
License: New BSD License
Keywords: django apps utils
Platform: UNKNOWN
Classifier: Development Status :: 3 - Alpha
Classifier: Environment :: Plugins
Classifier: Framework :: Django
Classifier: Intended Audience :: Developers
Classifier: License :: OSI Approved :: BSD License
Classifier: Programming Language :: Python
Classifier: Topic :: Software Development :: Libraries :: Python Modules
